NiukeJinrongXingyeMingqiBiMianshiXiaozhaoQiuzhiGonglve20212022/README.md
NiukeJinrongXingyeMingqiBiMianshiXiaozhaoQiuzhiGonglve20212022/__init__.py
NiukeJinrongXingyeMingqiBiMianshiXiaozhaoQiuzhiGonglve20212022/__main__.py
NiukeJinrongXingyeMingqiBiMianshiXiaozhaoQiuzhiGonglve20212022/file.epub
NiukeJinrongXingyeMingqiBiMianshiXiaozhaoQiuzhiGonglve20212022/index.html
NiukeJinrongXingyeMingqiBiMianshiXiaozhaoQiuzhiGonglve20212022/css/__init__.py
NiukeJinrongXingyeMingqiBiMianshiXiaozhaoQiuzhiGonglve20212022/css/annotations.css
NiukeJinrongXingyeMingqiBiMianshiXiaozhaoQiuzhiGonglve20212022/css/main.css
NiukeJinrongXingyeMingqiBiMianshiXiaozhaoQiuzhiGonglve20212022/css/normalize.css
NiukeJinrongXingyeMingqiBiMianshiXiaozhaoQiuzhiGonglve20212022/css/popup.css
NiukeJinrongXingyeMingqiBiMianshiXiaozhaoQiuzhiGonglve20212022/font/__init__.py
NiukeJinrongXingyeMingqiBiMianshiXiaozhaoQiuzhiGonglve20212022/font/fontello.eot
NiukeJinrongXingyeMingqiBiMianshiXiaozhaoQiuzhiGonglve20212022/font/fontello.svg
NiukeJinrongXingyeMingqiBiMianshiXiaozhaoQiuzhiGonglve20212022/font/fontello.ttf
NiukeJinrongXingyeMingqiBiMianshiXiaozhaoQiuzhiGonglve20212022/font/fontello.woff
NiukeJinrongXingyeMingqiBiMianshiXiaozhaoQiuzhiGonglve20212022/img/__init__.py
NiukeJinrongXingyeMingqiBiMianshiXiaozhaoQiuzhiGonglve20212022/img/annotator-glyph-sprite.png
NiukeJinrongXingyeMingqiBiMianshiXiaozhaoQiuzhiGonglve20212022/img/annotator-icon-sprite.png
NiukeJinrongXingyeMingqiBiMianshiXiaozhaoQiuzhiGonglve20212022/img/apple-touch-icon.png
NiukeJinrongXingyeMingqiBiMianshiXiaozhaoQiuzhiGonglve20212022/img/cancelfullscreen.png
NiukeJinrongXingyeMingqiBiMianshiXiaozhaoQiuzhiGonglve20212022/img/close.png
NiukeJinrongXingyeMingqiBiMianshiXiaozhaoQiuzhiGonglve20212022/img/fullscreen.png
NiukeJinrongXingyeMingqiBiMianshiXiaozhaoQiuzhiGonglve20212022/img/loader.gif
NiukeJinrongXingyeMingqiBiMianshiXiaozhaoQiuzhiGonglve20212022/img/menu-icon.png
niuke_jinrong_xingye_mingqi_bi_mianshi_xiaozhao_qiuzhi_gonglve_2021_2022-2024.3.6.0.dist-info/METADATA
niuke_jinrong_xingye_mingqi_bi_mianshi_xiaozhao_qiuzhi_gonglve_2021_2022-2024.3.6.0.dist-info/WHEEL
niuke_jinrong_xingye_mingqi_bi_mianshi_xiaozhao_qiuzhi_gonglve_2021_2022-2024.3.6.0.dist-info/entry_points.txt
niuke_jinrong_xingye_mingqi_bi_mianshi_xiaozhao_qiuzhi_gonglve_2021_2022-2024.3.6.0.dist-info/top_level.txt
niuke_jinrong_xingye_mingqi_bi_mianshi_xiaozhao_qiuzhi_gonglve_2021_2022-2024.3.6.0.dist-info/RECORD
